canni.py
canni/__init__.py
canni/canni.py
canni/templates/index.html
canni/templates/switch.html
canni-3.0.0.dist-info/LICENSE
canni-3.0.0.dist-info/METADATA
canni-3.0.0.dist-info/WHEEL
canni-3.0.0.dist-info/top_level.txt
canni-3.0.0.dist-info/RECORD
