Metadata-Version: 2.1
Name: canni
Version: 3.0.0
Summary: Create static html pages (with additional javascript functionality to copy text more easily) based on a dataset used for bronk.
Home-page: https://gitlab.com/networkjanitor/canni
Author: Xyoz Netsphere
Author-email: nanoowl@xyooz.net
License: MIT
Platform: UNKNOWN
Classifier: Development Status :: 5 - Production/Stable
Classifier: License :: OSI Approved :: MIT License
Classifier: Programming Language :: Python :: 3
Classifier: Programming Language :: Python :: 3.7
Requires-Dist: jinja2
Requires-Dist: PyYAML
